purecpp_libs/RagPUREAI_libs.cpython-311-x86_64-linux-gnu.so
purecpp_libs/__init__.py
purecpp_libs-1.0.5.dist-info/METADATA
purecpp_libs-1.0.5.dist-info/WHEEL
purecpp_libs-1.0.5.dist-info/top_level.txt
purecpp_libs-1.0.5.dist-info/RECORD
